{
  "_class": "symbolInstance",
  "booleanOperation": -1,
  "do_objectID": "23540E45-7B2E-437D-B970-C895C3C82CD2",
  "exportOptions": {
    "_class": "exportOptions",
    "do_objectID": "5A720940-CE70-4E85-8A3A-34E44B8A1E7B",
    "exportFormats": [
    ],
    "includedLayerIds": [
    ],
    "layerOptions": 0,
    "shouldTrim": false
  },
  "frame": {
    "_class": "rect",
    "constrainProportions": false,
    "do_objectID": "281FFAE6-B978-45F7-B0B6-BDC45EC9955E",
    "height": 57,
    "width": 145,
    "x": 41,
    "y": 461
  },
  "horizontalSpacing": 0,
  "isFixedToViewport": false,
  "isFlippedHorizontal": false,
  "isFlippedVertical": false,
  "isLocked": false,
  "isVisible": true,
  "layerListExpandedType": 0,
  "name": "Back Copy",
  "nameIsFixed": false,
  "overrideValues": [
  ],
  "resizingConstraint": 63,
  "resizingType": 0,
  "rotation": 0,
  "scale": 1,
  "shouldBreakMaskChain": false,
  "style": {
    "_class": "style",
    "do_objectID": "9F3356BD-0BD6-4F0F-8756-ACB1905BF487",
    "endMarkerType": 0,
    "miterLimit": 10,
    "startMarkerType": 0,
    "windingRule": 1
  },
  "symbolID": "E3CD97EE-E77D-408A-A260-2BB61960B0D9",
  "userInfo": {
    "com.invision.prototype": {
      "backgroundOpacity": 0,
      "closeOnClickOutside": 1,
      "componentType": "SRLink",
      "fixOverlayPosition": 1,
      "gesture": 7,
      "linkType": 0,
      "maintainScrollPositionAfterGesture": 0,
      "maintainScrollPositionAfterRedirect": 0,
      "openURLInNewWindow": 0,
      "overlayPosition": 0,
      "overlayTransition": 0,
      "redirectAfter": 0,
      "reverseTransitionOnClose": 1,
      "scrollToPosition": 0,
      "smoothScrolling": 0,
      "stayOnTargetScreen": 0,
      "targetArtboardID": "45EA189A-8E49-40AF-9BBA-1E3ADB3A3BCA",
      "transition": 1
    }
  },
  "verticalSpacing": 0
}