{
  "_class": "symbolInstance",
  "booleanOperation": -1,
  "do_objectID": "88216D92-E404-45FD-A12E-F57A21C51A5B",
  "exportOptions": {
    "_class": "exportOptions",
    "do_objectID": "0A33FB84-9A7B-471C-B83A-BC8BA2B5B26B",
    "exportFormats": [
    ],
    "includedLayerIds": [
    ],
    "layerOptions": 0,
    "shouldTrim": false
  },
  "frame": {
    "_class": "rect",
    "constrainProportions": false,
    "do_objectID": "4ADEDDE6-70DB-4E0D-A9D8-66297A3C78BE",
    "height": 24,
    "width": 23,
    "x": 321,
    "y": 113
  },
  "horizontalSpacing": 0,
  "isFixedToViewport": false,
  "isFlippedHorizontal": false,
  "isFlippedVertical": false,
  "isLocked": false,
  "isVisible": true,
  "layerListExpandedType": 0,
  "name": "X Copy 6",
  "nameIsFixed": false,
  "overrideValues": [
  ],
  "resizingConstraint": 63,
  "resizingType": 0,
  "rotation": 0,
  "scale": 1,
  "shouldBreakMaskChain": false,
  "style": {
    "_class": "style",
    "do_objectID": "54E99A23-E97E-4A2F-A32E-0D0E8CA0A389",
    "endMarkerType": 0,
    "miterLimit": 10,
    "startMarkerType": 0,
    "windingRule": 1
  },
  "symbolID": "3F6B2871-CA01-4078-A796-8DEAC26CD4CB",
  "userInfo": {
    "com.invision.prototype": {
      "backgroundOpacity": 0,
      "closeOnClickOutside": 1,
      "componentType": "SRLink",
      "fixOverlayPosition": 1,
      "gesture": 7,
      "linkType": 0,
      "maintainScrollPositionAfterGesture": 0,
      "maintainScrollPositionAfterRedirect": 0,
      "openURLInNewWindow": 0,
      "overlayPosition": 0,
      "overlayTransition": 0,
      "redirectAfter": 0,
      "reverseTransitionOnClose": 1,
      "scrollToPosition": 0,
      "smoothScrolling": 0,
      "stayOnTargetScreen": 0,
      "targetArtboardID": "C887C9C1-FEC4-4BCD-89E7-2317CA3C28A0",
      "transition": 1
    }
  },
  "verticalSpacing": 0
}